Workbook

Sheet Inventory Data
A1: Item ID | B1: Product Name | C1: Category | D1: Supplier | E1: Warehouse | F1: Unit Cost | G1: Selling Price | H1: Stock Qty | I1: Reorder Level | J1: Stock Value | K1: Profit Margin | L1: Status | M1: Days Since Restock
A2: INV001 | B2: Laptop | C2: Electronics | D2: TechSupplies Ltd | E2: Mumbai WH | F2: 3359 | G2: 5053 | H2: 91 | I2: 34 | J2: =F2*H2 -> 305669 | K2: =IF(F2>0,(G2-F2)/F2,0) -> 0.50431676 | L2: =IF(H2=0,"⛔ OUT OF STOCK",IF(H2<I2,"🔴 Low Stock","✅ In Stock")) -> ✅ In Stock | M2: 18
A3: INV002 | B3: Mobile | C3: Electronics | D3: TechSupplies Ltd | E3: Delhi WH | F3: 759 | G3: 1063 | H3: 196 | I3: 53 | J3: =F3*H3 -> 148764 | K3: =IF(F3>0,(G3-F3)/F3,0) -> 0.40052701 | L3: =IF(H3=0,"⛔ OUT OF STOCK",IF(H3<I3,"🔴 Low Stock","✅ In Stock")) -> ✅ In Stock | M3: 80
A4: INV003 | B4: Tablet | C4: Electronics | D4: TechSupplies Ltd | E4: Bangalore WH | F4: 4058 | G4: 5517 | H4: 110 | I4: 70 | J4: =F4*H4 -> 446380 | K4: =IF(F4>0,(G4-F4)/F4,0) -> 0.35953672 | L4: =IF(H4=0,"⛔ OUT OF STOCK",IF(H4<I4,"🔴 Low Stock","✅ In Stock")) -> ✅ In Stock | M4: 50
A5: INV004 | B5: Smartwatch | C5: Electronics | D5: TechSupplies Ltd | E5: Bangalore WH | F5: 1791 | G5: 2367 | H5: 91 | I5: 74 | J5: =F5*H5 -> 162981 | K5: =IF(F5>0,(G5-F5)/F5,0) -> 0.32160804 | L5: =IF(H5=0,"⛔ OUT OF STOCK",IF(H5<I5,"🔴 Low Stock","✅ In Stock")) -> ✅ In Stock | M5: 11
A6: INV005 | B6: Earphones | C6: Electronics | D6: TechSupplies Ltd | E6: Bangalore WH | F6: 4381 | G6: 7631 | H6: 44 | I6: 50 | J6: =F6*H6 -> 192764 | K6: =IF(F6>0,(G6-F6)/F6,0) -> 0.74183976 | L6: =IF(H6=0,"⛔ OUT OF STOCK",IF(H6<I6,"🔴 Low Stock","✅ In Stock")) -> 🔴 Low Stock | M6: 52
A7: INV006 | B7: Camera | C7: Electronics | D7: TechSupplies Ltd | E7: Mumbai WH | F7: 399 | G7: 564 | H7: 3 | I7: 47 | J7: =F7*H7 -> 1197 | K7: =IF(F7>0,(G7-F7)/F7,0) -> 0.41353383 | L7: =IF(H7=0,"⛔ OUT OF STOCK",IF(H7<I7,"🔴 Low Stock","✅ In Stock")) -> 🔴 Low Stock | M7: 47
A8: INV007 | B8: T-Shirt | C8: Clothing | D8: Fashion World | E8: Mumbai WH | F8: 4427 | G8: 5598 | H8: 265 | I8: 77 | J8: =F8*H8 -> 1173155 | K8: =IF(F8>0,(G8-F8)/F8,0) -> 0.26451321 | L8: =IF(H8=0,"⛔ OUT OF STOCK",IF(H8<I8,"🔴 Low Stock","✅ In Stock")) -> ✅ In Stock | M8: 78
A9: INV008 | B9: Jeans | C9: Clothing | D9: Fashion World | E9: Mumbai WH | F9: 3840 | G9: 7608 | H9: 183 | I9: 28 | J9: =F9*H9 -> 702720 | K9: =IF(F9>0,(G9-F9)/F9,0) -> 0.98125 | L9: =IF(H9=0,"⛔ OUT OF STOCK",IF(H9<I9,"🔴 Low Stock","✅ In Stock")) -> ✅ In Stock | M9: 21
A10: INV009 | B10: Jacket | C10: Clothing | D10: Fashion World | E10: Mumbai WH | F10: 3668 | G10: 6148 | H10: 90 | I10: 80 | J10: =F10*H10 -> 330120 | K10: =IF(F10>0,(G10-F10)/F10,0) -> 0.67611778 | L10: =IF(H10=0,"⛔ OUT OF STOCK",IF(H10<I10,"🔴 Low Stock","✅ In Stock")) -> ✅ In Stock | M10: 5
A11: INV010 | B11: Saree | C11: Clothing | D11: Fashion World | E11: Chennai WH | F11: 949 | G11: 1156 | H11: 242 | I11: 63 | J11: =F11*H11 -> 229658 | K11: =IF(F11>0,(G11-F11)/F11,0) -> 0.21812434 | L11: =IF(H11=0,"⛔ OUT OF STOCK",IF(H11<I11,"🔴 Low Stock","✅ In Stock")) -> ✅ In Stock | M11: 11
A12: INV011 | B12: Kurta | C12: Clothing | D12: Fashion World | E12: Delhi WH | F12: 3535 | G12: 6029 | H12: 73 | I12: 39 | J12: =F12*H12 -> 258055 | K12: =IF(F12>0,(G12-F12)/F12,0) -> 0.70551627 | L12: =IF(H12=0,"⛔ OUT OF STOCK",IF(H12<I12,"🔴 Low Stock","✅ In Stock")) -> ✅ In Stock | M12: 49
A13: INV012 | B13: Shoes | C13: Clothing | D13: Fashion World | E13: Delhi WH | F13: 2750 | G13: 3598 | H13: 207 | I13: 32 | J13: =F13*H13 -> 569250 | K13: =IF(F13>0,(G13-F13)/F13,0) -> 0.30836364 | L13: =IF(H13=0,"⛔ OUT OF STOCK",IF(H13<I13,"🔴 Low Stock","✅ In Stock")) -> ✅ In Stock | M13: 82
... A37: INV036 | B37: Pliers | C37: Tools | D37: ToolMaster | E37: Mumbai WH | F37: 870 | G37: 1734 | H37: 202 | I37: 45 | J37: =F37*H37 -> 175740 | K37: =IF(F37>0,(G37-F37)/F37,0) -> 0.99310345 | L37: =IF(H37=0,"⛔ OUT OF STOCK",IF(H37<I37,"🔴 Low Stock","✅ In Stock")) -> ✅ In Stock | M37: 34

Sheet Dashboard
A1: 📦 INVENTORY MANAGEMENT DASHBOARD
B4: 📦 Total Items | F4: 💰 Total Stock Value | J4: ⚠ Low Stock Items | N4: ⛔ Out of Stock | R4: 📊 Avg Margin
B5: =COUNTA('Inventory Data'!A2:A37) -> 36 | F5: =SUM('Inventory Data'!J2:J37) -> 13220607 | J5: =COUNTIF('Inventory Data'!L2:L37,"🔴 Low Stock") -> 4 | N5: =COUNTIF('Inventory Data'!L2:L37,"⛔ OUT OF STOCK") -> 0 | R5: =AVERAGE('Inventory Data'!K2:K37) -> 0.61645451
A12: Category | B12: Items | C12: Total Value | D12: Low Stock
A13: Electronics | B13: =COUNTIF('Inventory Data'!C2:C37,A13) -> 6 | C13: =SUMIF('Inventory Data'!C2:C37,A13,'Inventory Data'!J2:J37) -> 1257755 | D13: =COUNTIFS('Inventory Data'!C2:C37,A13,'Inventory Data'!L2:L37,"🔴 Low Stock") -> 2
A14: Clothing | B14: =COUNTIF('Inventory Data'!C2:C37,A14) -> 6 | C14: =SUMIF('Inventory Data'!C2:C37,A14,'Inventory Data'!J2:J37) -> 3262958 | D14: =COUNTIFS('Inventory Data'!C2:C37,A14,'Inventory Data'!L2:L37,"🔴 Low Stock") -> 0
A15: Furniture | B15: =COUNTIF('Inventory Data'!C2:C37,A15) -> 6 | C15: =SUMIF('Inventory Data'!C2:C37,A15,'Inventory Data'!J2:J37) -> 1246173 | D15: =COUNTIFS('Inventory Data'!C2:C37,A15,'Inventory Data'!L2:L37,"🔴 Low Stock") -> 2
A16: FMCG | B16: =COUNTIF('Inventory Data'!C2:C37,A16) -> 6 | C16: =SUMIF('Inventory Data'!C2:C37,A16,'Inventory Data'!J2:J37) -> 2670242 | D16: =COUNTIFS('Inventory Data'!C2:C37,A16,'Inventory Data'!L2:L37,"🔴 Low Stock") -> 0
A17: Stationery | B17: =COUNTIF('Inventory Data'!C2:C37,A17) -> 6 | C17: =SUMIF('Inventory Data'!C2:C37,A17,'Inventory Data'!J2:J37) -> 2225052 | D17: =COUNTIFS('Inventory Data'!C2:C37,A17,'Inventory Data'!L2:L37,"🔴 Low Stock") -> 0
A18: Tools | B18: =COUNTIF('Inventory Data'!C2:C37,A18) -> 6 | C18: =SUMIF('Inventory Data'!C2:C37,A18,'Inventory Data'!J2:J37) -> 2558427 | D18: =COUNTIFS('Inventory Data'!C2:C37,A18,'Inventory Data'!L2:L37,"🔴 Low Stock") -> 0

Sheet Reorder Alerts
A1: 🔴 REORDER ALERT SYSTEM — Items Needing Attention
A3: Item ID | B3: Product | C3: Category | D3: Stock Qty | E3: Reorder Level | F3: Action Required
A4: ⚠ Items listed below need immediate reordering
A5: INV005 | B5: Earphones | C5: Electronics | D5: 44 | E5: 50 | F5: Order 56 units
A6: INV006 | B6: Camera | C6: Electronics | D6: 3 | E6: 47 | F6: Order 94 units
A7: INV017 | B7: Sofa | C7: Furniture | D7: 60 | E7: 74 | F7: Order 64 units
A8: INV018 | B8: Bed Frame | C8: Furniture | D8: 5 | E8: 57 | F8: Order 102 units

Sheet VBA Macros Code
A1: 💻 Inventory VBA Macros — Alt+F11 → Insert Module → Paste
A3: ' ================================================================ ' MACRO 1: Highlight All Low Stock Items ' ================================================================ Sub HighlightLowStock() Dim ws As Worksheet Dim lastRow As Long, i As Long Set ws = ThisWorkbook.Sheets("Inventory Data") lastRow = ws.Cells(ws.Rows.Count, 1).End(xlUp).Row For i = 2 To lastRow Dim stock As Long Dim reorder As Long stock = ws.Cells(i, 8).Value reorder = ws.Cells(i, 9).Value If stock = 0 Then ws.Rows(i).Interior.Color = RGB(255, 199, 206) ' Red ElseIf stock < reorder Then ws.Rows(i).Interior.Color = RGB(255, 242, 204) ' Yellow Else ws.Rows(i).Interior.ColorIndex = xlNone ' Clear End If Next i MsgBox "Stock status colors applied!", vbInformation End Sub ' ================================================================ ' MACRO 2: Generate Low Stock Report in New Sheet ' ================================================================ Sub GenerateLowStockReport() Dim wsSrc As Worksheet, wsDst As Worksheet Dim lastRow As Long, i As Long, dstRow As Long Set wsSrc = ThisWorkbook.Sheets("Inventory Data") lastRow = wsSrc.Cells(wsSrc.Rows.Count, 1).End(xlUp).Row ' Delete old report if exists On Error Resume Next Application.DisplayAlerts = False ThisWorkbook.Sheets("Low Stock Report").Delete Application.DisplayAlerts = True On Error GoTo 0 ' Create new sheet Set wsDst = ThisWorkbook.Sheets.Add(After:=ThisWorkbook.Sheets(ThisWorkbook.Sheets.Count)) wsDst.Name = "Low Stock Report" ' Headers Dim headers As Variant headers = Array("Item ID", "Product", "Category", "Stock Qty", "Reorder Level", "Shortage") For i = 0 To 5 wsDst.Cells(1, i + 1).Value = headers(i) wsDst.Cells(1, i + 1).Font.Bold = True wsDst.Cells(1, i + 1).Interior.Color = RGB(31, 56, 100) wsDst.Cells(1, i + 1).Font.Color = RGB(255, 255, 255) Next i dstRow = 2 For i = 2 To lastRow If wsSrc.Cells(i, 8).Value < wsSrc.Cells(i, 9).Value Then wsDst.Cells(dstRow, 1).Value = wsSrc.Cells(i, 1).Value wsDst.Cells(dstRow, 2).Value = wsSrc.Cells(i, 2).Value wsDst.Cells(dstRow, 3).Value = wsSrc.Cells(i, 3).Value wsDst.Cells(dstRow, 4).Value = wsSrc.Cells(i, 8).Value wsDst.Cells(dstRow, 5).Value = wsSrc.Cells(i, 9).Value wsDst.Cells(dstRow, 6).Value = wsSrc.Cells(i, 9).Value - wsSrc.Cells(i, 8).Value dstRow = dstRow + 1 End If Next i MsgBox "Low Stock Report created! " & (dstRow - 2) & " items need reordering.", vbInformation End Sub ' ================================================================ ' MACRO 3: Update Stock Quantity via InputBox ' ================================================================ Sub UpdateStock() Dim ws As Worksheet Dim itemID As String, newQty As Long Dim lastRow As Long, i As Long, found As Boolean Set ws = ThisWorkbook.Sheets("Inventory Data") lastRow = ws.Cells(ws.Rows.Count, 1).End(xlUp).Row itemID = InputBox("Enter Item ID to update (e.g., INV001):", "Update Stock") If itemID = "" Then Exit Sub For i = 2 To lastRow If UCase(ws.Cells(i, 1).Value) = UCase(itemID) Then found = True Dim currentQty As Long currentQty = ws.Cells(i, 8).Value newQty = InputBox("Current stock: " & currentQty & Chr(10) & "Enter new quantity:", "Update Stock", currentQty) ws.Cells(i, 8).Value = newQty MsgBox "Stock updated for " & ws.Cells(i, 2).Value & ": " & newQty & " units", vbInformation Exit For End If Next i If Not found Then MsgBox "Item ID not found: " & itemID, vbExclamation End Sub ' ================================================================ ' MACRO 4: Calculate Total Inventory Value by Category ' ================================================================ Sub CategoryValueSummary() Dim ws As Worksheet Dim lastRow As Long, i As Long Dim catValues As Object Set catValues = CreateObject("Scripting.Dictionary") Set ws = ThisWorkbook.Sheets("Inventory Data") lastRow = ws.Cells(ws.Rows.Count, 1).End(xlUp).Row For i = 2 To lastRow Dim cat As String Dim val As Double cat = ws.Cells(i, 3).Value val = ws.Cells(i, 10).Value If catValues.Exists(cat) Then catValues(cat) = catValues(cat) + val Else catValues.Add cat, val End If Next i Dim msg As String msg = "=== INVENTORY VALUE BY CATEGORY ===" & Chr(10) Dim key As Variant For Each key In catValues.Keys msg = msg & key & ": Rs." & Format(catValues(key), "#,##0") & Chr(10) Next key MsgBox msg, vbInformation, "Category Value Summary" End Sub
